CHANGES.rst
LICENSE.rst
MANIFEST.in
README.rst
requirements.txt
setup.py
defaults/modules.py
defaults/template.js
wsa_cli/__init__.py
wsa_cli/wsa.py
wsa_cli.egg-info/PKG-INFO
wsa_cli.egg-info/SOURCES.txt
wsa_cli.egg-info/dependency_links.txt
wsa_cli.egg-info/entry_points.txt
wsa_cli.egg-info/requires.txt
wsa_cli.egg-info/top_level.txt