Metadata-Version: 1.1
Name: wsa-cli
Version: 0.0.2
Summary: Command line tool to generate basic folder, file structure for a WSA module.
Home-page: https://github.com/neurosnap/wsa-cli
Author: Eric Bower
Author-email: neurosnap@gmail.com
License: The MIT License
